{
  "credit": "Made with Blockbench",
  "parent": "builtin/entity",
  "texture_size": [
    96,
    96
  ],
  "display": {
    "thirdperson_righthand": {
      "rotation": [
        60,
        0,
        0
      ],
      "translation": [
        0,
        1.5,
        -1
      ],
      "scale": [
        0.2,
        0.2,
        0.2
      ]
    },
    "thirdperson_lefthand": {
      "rotation": [
        60,
        0,
        0
      ],
      "translation": [
        0,
        1.5,
        -1
      ],
      "scale": [
        0.2,
        0.2,
        0.2
      ]
    },
    "firstperson_righthand": {
      "rotation": [
        0,
        180,
        0
      ],
      "translation": [
        4,
        0,
        0
      ],
      "scale": [
        0.3,
        0.3,
        0.3
      ]
    },
    "firstperson_lefthand": {
      "rotation": [
        0,
        180,
        0
      ],
      "translation": [
        4,
        0,
        0
      ],
      "scale": [
        0.3,
        0.3,
        0.3
      ]
    },
    "ground": {
      "scale": [
        0.3,
        0.3,
        0.3
      ]
    },
    "gui": {
      "rotation": [
        26,
        -120,
        0
      ],
      "translation": [
        0,
        -3,
        0
      ],
      "scale": [
        0.4,
        0.4,
        0.4
      ]
    },
    "head": {
      "translation": [
        0,
        -6.5,
        0
      ]
    },
    "fixed": {
      "translation": [
        0,
        -3.25,
        -2.25
      ],
      "scale": [
        0.4,
        0.4,
        0.4
      ]
    }
  },
  "textures": {
    "particle": "papercraft_magic_decoration:block/long_storage_table"
  }
}