{
  "_fv": 57,
  "_type": "recipe",
  "definition": {
    "recipeType": "Crafting",
    "recipeRetstackSize": 1,
    "group": "",
    "cookingBookCategory": "MISC",
    "xpReward": 0.0,
    "cookingTime": 200,
    "craftingBookCategory": "MISC",
    "recipeShapeless": false,
    "recipeSlots": [
      {
        "value": "Items.QUARTZ"
      },
      {
        "value": "Items.GOLD_INGOT"
      },
      {
        "value": "Items.QUARTZ"
      },
      {
        "value": "Items.QUARTZ"
      },
      {
        "value": "Blocks.POLISHED_DEEPSLATE"
      },
      {
        "value": "Items.QUARTZ"
      },
      {
        "value": "Items.QUARTZ"
      },
      {
        "value": "Blocks.CALCITE"
      },
      {
        "value": "Items.QUARTZ"
      }
    ],
    "recipeReturnStack": {
      "value": "CUSTOM:MarbleAngel"
    },
    "name": "marble_angel_formulas",
    "namespace": "mod"
  }
}