{
	"format_version": "1.8.0",
	"animations": {
		"animation.air_flow_carp.idle": {
			"animation_length": 10,
			"bones": {
				"left_body": {
					"rotation": {
						"0.0": {
							"vector": [0, 0, 0]
						},
						"2.5": {
							"vector": [0, 0, 5],
							"easing": "easeInOutQuad"
						},
						"5.0": {
							"vector": [0, 0, 0],
							"easing": "easeInOutQuad"
						},
						"7.5": {
							"vector": [0, 0, 5],
							"easing": "easeInOutQuad"
						},
						"10.0": {
							"vector": [0, 0, 0],
							"easing": "easeInOutQuad"
						}
					}
				},
				"left_hand_fin": {
					"rotation": {
						"0.0": {
							"vector": [0, 0, 0]
						},
						"3.3333": {
							"vector": [0, 0, -10],
							"easing": "easeOutQuad"
						},
						"5.0": {
							"vector": [0, 0, 0],
							"easing": "easeInOutQuad"
						},
						"8.3333": {
							"vector": [0, 0, -10],
							"easing": "easeOutQuad"
						},
						"10.0": {
							"vector": [0, 0, 0],
							"easing": "easeInOutQuad"
						}
					}
				},
				"right_body": {
					"rotation": {
						"0.0": {
							"vector": [0, 0, 0]
						},
						"2.5": {
							"vector": [0, 0, -5],
							"easing": "easeInOutQuad"
						},
						"5.0": {
							"vector": [0, 0, 0],
							"easing": "easeInOutQuad"
						},
						"7.5": {
							"vector": [0, 0, -5],
							"easing": "easeInOutQuad"
						},
						"10.0": {
							"vector": [0, 0, 0],
							"easing": "easeInOutQuad"
						}
					}
				},
				"right_hand_fin": {
					"rotation": {
						"0.0": {
							"vector": [0, 0, 0]
						},
						"3.3333": {
							"vector": [0, 0, 10],
							"easing": "easeOutQuad"
						},
						"5.0": {
							"vector": [0, 0, 0],
							"easing": "easeInOutQuad"
						},
						"8.3333": {
							"vector": [0, 0, 10],
							"easing": "easeOutQuad"
						},
						"10.0": {
							"vector": [0, 0, 0],
							"easing": "easeInOutQuad"
						}
					}
				},
				"left_caudal_fin": {
					"rotation": {
						"0.0": {
							"vector": [0, 0, 0]
						},
						"1.0833": {
							"vector": [0, -10, 0],
							"easing": "easeInOutQuad"
						},
						"2.1667": {
							"vector": [0, 5, 0],
							"easing": "easeInOutQuad"
						},
						"3.3333": {
							"vector": [0, 0, 0],
							"easing": "easeInOutQuad"
						},
						"4.5": {
							"vector": [0, -10, 0],
							"easing": "easeInOutQuad"
						},
						"5.625": {
							"vector": [0, 5, 0],
							"easing": "easeInOutQuad"
						},
						"6.625": {
							"vector": [0, 0, 0],
							"easing": "easeInOutQuad"
						},
						"7.7083": {
							"vector": [0, -10, 0],
							"easing": "easeInOutQuad"
						},
						"8.8333": {
							"vector": [0, 5, 0],
							"easing": "easeInOutQuad"
						},
						"10.0": {
							"vector": [0, 0, 0],
							"easing": "easeInOutQuad"
						}
					}
				},
				"right_caudal_fin": {
					"rotation": {
						"0.0": {
							"vector": [0, 0, 0]
						},
						"1.0833": {
							"vector": [0, 10, 0],
							"easing": "easeInOutQuad"
						},
						"2.1667": {
							"vector": [0, -5, 0],
							"easing": "easeInOutQuad"
						},
						"3.3333": {
							"vector": [0, 0, 0],
							"easing": "easeInOutQuad"
						},
						"4.5": {
							"vector": [0, 10, 0],
							"easing": "easeInOutQuad"
						},
						"5.625": {
							"vector": [0, -5, 0],
							"easing": "easeInOutQuad"
						},
						"6.625": {
							"vector": [0, 0, 0],
							"easing": "easeInOutQuad"
						},
						"7.7083": {
							"vector": [0, 10, 0],
							"easing": "easeInOutQuad"
						},
						"8.8333": {
							"vector": [0, -5, 0],
							"easing": "easeInOutQuad"
						},
						"10.0": {
							"vector": [0, 0, 0],
							"easing": "easeInOutQuad"
						}
					}
				},
				"tentacle_1": {
					"rotation": {
						"0.0": {
							"vector": [0, 0, 0]
						},
						"1.25": {
							"vector": [-9.96271, -0.86717, -4.92442],
							"easing": "easeOutQuad"
						},
						"2.75": {
							"vector": [5, 0, 0],
							"easing": "easeInOutQuad"
						},
						"5.0": {
							"vector": [0, 0, 0],
							"easing": "easeInOutQuad"
						},
						"6.25": {
							"vector": [-10, 0, 0],
							"easing": "easeOutQuad"
						},
						"7.75": {
							"vector": [5, 0, 0],
							"easing": "easeInOutQuad"
						},
						"10.0": {
							"vector": [0, 0, 0],
							"easing": "easeInOutQuad"
						}
					}
				},
				"tentacle_2": {
					"rotation": {
						"0.0": {
							"vector": [0, 0, 0]
						},
						"2.1667": {
							"vector": [-10, 0, 0],
							"easing": "easeOutQuad"
						},
						"3.6667": {
							"vector": [5, 0, 0],
							"easing": "easeInOutQuad"
						},
						"5.0": {
							"vector": [0, 0, 0],
							"easing": "easeOutQuad"
						},
						"7.125": {
							"vector": [-9.96271, 0.86717, 4.92442],
							"easing": "easeOutQuad"
						},
						"8.625": {
							"vector": [5, 0, 0],
							"easing": "easeInOutQuad"
						},
						"10.0": {
							"vector": [0, 0, 0],
							"easing": "easeOutQuad"
						}
					}
				},
				"left_face_fin": {
					"rotation": {
						"0.0": {
							"vector": [0, 0, 0]
						},
						"2.5": {
							"vector": [0, 0, 5],
							"easing": "easeInOutQuad"
						},
						"5.0": {
							"vector": [0, 0, 0],
							"easing": "easeInOutQuad"
						},
						"7.5": {
							"vector": [0, 0, -5],
							"easing": "easeInOutQuad"
						},
						"10.0": {
							"vector": [0, 0, 0],
							"easing": "easeInOutQuad"
						}
					}
				},
				"right_face_fin": {
					"rotation": {
						"0.0": {
							"vector": [0, 0, 0]
						},
						"2.5": {
							"vector": [0, 0, -5],
							"easing": "easeInOutQuad"
						},
						"5.0": {
							"vector": [0, 0, 0],
							"easing": "easeInOutQuad"
						},
						"7.5": {
							"vector": [0, 0, 5],
							"easing": "easeInOutQuad"
						},
						"10.0": {
							"vector": [0, 0, 0],
							"easing": "easeInOutQuad"
						}
					}
				}
			}
		},
		"animation.air_flow_carp.flow": {
			"animation_length": 3,
			"bones": {
				"left_body": {
					"rotation": {
						"0.0": {
							"vector": [0, 0, 0]
						},
						"1.0": {
							"vector": [-4.98107, 0.43523, 4.98107],
							"easing": "easeInQuad"
						},
						"2.0": {
							"vector": [-0.13225, 1.29911, -4.98278],
							"easing": "easeOutQuad"
						},
						"3.0": {
							"vector": [0, 0, 0],
							"easing": "easeInOutQuad"
						}
					}
				},
				"right_body": {
					"rotation": {
						"0.0": {
							"vector": [0, 0, 0]
						},
						"1.0": {
							"vector": [-4.98107, 0.43523, -4.98107],
							"easing": "easeInQuad"
						},
						"2.0": {
							"vector": [-0.13225, 1.29911, 4.98278],
							"easing": "easeOutQuad"
						},
						"3.0": {
							"vector": [0, 0, 0],
							"easing": "easeInOutQuad"
						}
					}
				},
				"tail": {
					"rotation": {
						"0.0": {
							"vector": [0, 0, 0]
						},
						"1.5": {
							"vector": [2, 0, 0],
							"easing": "easeInOutQuad"
						},
						"3.0": {
							"vector": [0, 0, 0],
							"easing": "easeInOutQuad"
						}
					}
				},
				"left_caudal_fin": {
					"rotation": {
						"0.0": {
							"vector": [0, 0, 0]
						},
						"0.5": {
							"vector": [0, -15, 0],
							"easing": "easeInQuad"
						},
						"1.5": {
							"vector": [0, 10, 0],
							"easing": "easeOutQuad"
						},
						"3.0": {
							"vector": [0, 0, 0],
							"easing": "easeInOutQuad"
						}
					}
				},
				"right_caudal_fin": {
					"rotation": {
						"0.0": {
							"vector": [0, 0, 0]
						},
						"0.5": {
							"vector": [0, 15, 0],
							"easing": "easeInQuad"
						},
						"1.5": {
							"vector": [0, -10, 0],
							"easing": "easeOutQuad"
						},
						"3.0": {
							"vector": [0, 0, 0],
							"easing": "easeInOutQuad"
						}
					}
				},
				"tentacle_1": {
					"rotation": {
						"0.0": {
							"vector": [0, 0, 0]
						},
						"1.0": {
							"vector": [-9.96271, -0.86717, -4.92442],
							"easing": "easeOutQuad"
						},
						"2.0417": {
							"vector": [5, 0, 0],
							"easing": "easeInOutQuad"
						},
						"3.0": {
							"vector": [0, 0, 0],
							"easing": "easeInOutQuad"
						}
					}
				},
				"tentacle_2": {
					"rotation": {
						"0.0": {
							"vector": [0, 0, 0]
						},
						"1.0": {
							"vector": [-9.96271, 0.86717, 4.92442],
							"easing": "easeOutQuad"
						},
						"2.0417": {
							"vector": [5, 0, 0],
							"easing": "easeInOutQuad"
						},
						"3.0": {
							"vector": [0, 0, 0],
							"easing": "easeInOutQuad"
						}
					}
				},
				"left_face_fin": {
					"rotation": {
						"0.0": {
							"vector": [0, 0, 0]
						},
						"1.0": {
							"vector": [0, 5, 0],
							"easing": "easeInQuad"
						},
						"1.5": {
							"vector": [0, -10, 0],
							"easing": "easeInQuad"
						},
						"2.5": {
							"vector": [0, 5, 0],
							"easing": "easeOutQuad"
						},
						"3.0": {
							"vector": [0, 0, 0],
							"easing": "easeInOutQuad"
						}
					}
				},
				"right_face_fin": {
					"rotation": {
						"0.0": {
							"vector": [0, 0, 0]
						},
						"1.0": {
							"vector": [0, -5, 0],
							"easing": "easeInQuad"
						},
						"1.5": {
							"vector": [0, 10, 0],
							"easing": "easeInQuad"
						},
						"2.5": {
							"vector": [0, -5, 0],
							"easing": "easeOutQuad"
						},
						"3.0": {
							"vector": [0, 0, 0],
							"easing": "easeInOutQuad"
						}
					}
				}
			}
		}
	},
	"geckolib_format_version": 2
}